FixedPointJAX/FixedPointJAX.py
FixedPointJAX/__init__.py
tests/__init__.py
tests/test.py
FixedPointJAX-0.0.25.dist-info/LICENSE
FixedPointJAX-0.0.25.dist-info/METADATA
FixedPointJAX-0.0.25.dist-info/WHEEL
FixedPointJAX-0.0.25.dist-info/top_level.txt
FixedPointJAX-0.0.25.dist-info/RECORD
