Metadata-Version: 2.1
Name: FixedPointJAX
Version: 0.0.25
Summary: Fixed-point iterations for root finding implemented in JAX
Home-page: https://github.com/esbenscriver/FixedPointJAX.git
Author: Esben Scriver Andersen
Author-email: esbenscriver@gmail.com
Classifier: Programming Language :: Python :: 3
Classifier: License :: OSI Approved :: MIT License
Classifier: Operating System :: OS Independent
Requires-Python: >=3.6
License-File: LICENSE
Requires-Dist: jax
